MANIFEST.in
README.md
requirements.txt
setup.cfg
setup.py
pgcrypt_dumper/__init__.py
pgcrypt_dumper/connector.py
pgcrypt_dumper/copy.py
pgcrypt_dumper/dumper.py
pgcrypt_dumper/errors.py
pgcrypt_dumper/metadata.py
pgcrypt_dumper/query_path.py
pgcrypt_dumper/query_template.py
pgcrypt_dumper/random_name.py
pgcrypt_dumper.egg-info/PKG-INFO
pgcrypt_dumper.egg-info/SOURCES.txt
pgcrypt_dumper.egg-info/dependency_links.txt
pgcrypt_dumper.egg-info/not-zip-safe
pgcrypt_dumper.egg-info/requires.txt
pgcrypt_dumper.egg-info/top_level.txt
pgcrypt_dumper/queryes/attributes.sql
pgcrypt_dumper/queryes/copy_from.sql
pgcrypt_dumper/queryes/copy_to.sql
pgcrypt_dumper/queryes/prepare.sql