Metadata-Version: 2.1
Name: pgcrypt-dumper
Version: 0.0.2
Summary: Library for read and write PGCrypt format between PostgreSQL and file.
Home-page: https://github.com/0xMihalich/pgcrypt_dumper
Author: 0xMihalich
Author-email: bayanmobile87@gmail.com
License-File: README.md
Requires-Dist: pgcopylib==0.0.3
Requires-Dist: pgcrypt==0.0.4
Requires-Dist: psycopg>=3.2.9
